zaishiyishiheji/__init__.py
zaishiyishiheji/data/三朵鲜花.doc
zaishiyishiheji/data/三朵鲜花.pdf
zaishiyishiheji/data/仪矩之行.doc
zaishiyishiheji/data/仪矩之行.pdf
zaishiyishiheji/data/再试一试.doc
zaishiyishiheji/data/再试一试.pdf
zaishiyishiheji/data/再试一试合集.doc
zaishiyishiheji/data/再试一试合集.pdf
zaishiyishiheji/data/再试一试请继续.doc
zaishiyishiheji/data/再试一试请继续.pdf
zaishiyishiheji/data/岸芷汀兰.doc
zaishiyishiheji/data/岸芷汀兰.pdf
zaishiyishiheji/data/自由自在.doc
zaishiyishiheji/data/自由自在.pdf
zaishiyishiheji-0.0.4.dist-info/licenses/LICENSE
zaishiyishiheji-0.0.4.dist-info/METADATA
zaishiyishiheji-0.0.4.dist-info/WHEEL
zaishiyishiheji-0.0.4.dist-info/top_level.txt
zaishiyishiheji-0.0.4.dist-info/RECORD
