Metadata-Version: 2.4
Name: zaishiyishiheji
Version: 0.0.4
Summary: 王梓明写的故事
Home-page: http://www.sidaxiake.cn/
Author: 王梓明
Author-email: 1272660211@qq.com
Classifier: Programming Language :: Python :: 3
Classifier: Operating System :: OS Independent
License-File: LICENSE
Dynamic: author
Dynamic: author-email
Dynamic: classifier
Dynamic: description
Dynamic: description-content-type
Dynamic: home-page
Dynamic: license-file
Dynamic: summary
